configurations/__init__.py
configurations/__main__.py
configurations/asgi.py
configurations/base.py
configurations/decorators.py
configurations/fastcgi.py
configurations/importer.py
configurations/management.py
configurations/sphinx.py
configurations/utils.py
configurations/values.py
configurations/version.py
configurations/wsgi.py
django_configurations-2.5.1.dist-info/AUTHORS
django_configurations-2.5.1.dist-info/LICENSE
django_configurations-2.5.1.dist-info/METADATA
django_configurations-2.5.1.dist-info/WHEEL
django_configurations-2.5.1.dist-info/entry_points.txt
django_configurations-2.5.1.dist-info/top_level.txt
django_configurations-2.5.1.dist-info/RECORD
