Metadata-Version: 2.1
Name: django-configurations
Version: 2.5.1
Summary: A helper for organizing Django settings.
Home-page: https://django-configurations.readthedocs.io/
Author: Jannis Leidel
Author-email: jannis@leidel.info
License: BSD
Project-URL: Source, https://github.com/jazzband/django-configurations
Classifier: Development Status :: 5 - Production/Stable
Classifier: Framework :: Django
Classifier: Framework :: Django :: 3.2
Classifier: Framework :: Django :: 4.1
Classifier: Framework :: Django :: 4.2
Classifier: Framework :: Django :: 5.0
Classifier: Intended Audience :: Developers
Classifier: License :: OSI Approved :: BSD License
Classifier: Operating System :: OS Independent
Classifier: Programming Language :: Python
Classifier: Programming Language :: Python :: 3
Classifier: Programming Language :: Python :: 3 :: Only
Classifier: Programming Language :: Python :: 3.8
Classifier: Programming Language :: Python :: 3.9
Classifier: Programming Language :: Python :: 3.10
Classifier: Programming Language :: Python :: 3.11
Classifier: Programming Language :: Python :: 3.12
Classifier: Programming Language :: Python :: Implementation :: PyPy
Classifier: Topic :: Utilities
Requires-Python: >=3.8, <4.0
License-File: LICENSE
License-File: AUTHORS
Requires-Dist: django>=3.2
Provides-Extra: cache
Requires-Dist: django-cache-url; extra == "cache"
Provides-Extra: database
Requires-Dist: dj-database-url; extra == "database"
Provides-Extra: email
Requires-Dist: dj-email-url; extra == "email"
Provides-Extra: search
Requires-Dist: dj-search-url; extra == "search"
Provides-Extra: testing
Requires-Dist: django-cache-url>=1.0.0; extra == "testing"
Requires-Dist: dj-database-url; extra == "testing"
Requires-Dist: dj-email-url; extra == "testing"
Requires-Dist: dj-search-url; extra == "testing"
